bagulho/__init__.py
bagulho/cli.py
bagulho_renan_estudo-0.1.0.dist-info/entry_points.txt
bagulho_renan_estudo-0.1.0.dist-info/METADATA
bagulho_renan_estudo-0.1.0.dist-info/WHEEL
bagulho_renan_estudo-0.1.0.dist-info/RECORD
